MANIFEST.in
README.rst
__init__.py
comments.py
eclaircie
email_obfuscator.py
page.py
rst.py
rst_ext.py
setup.cfg
setup.py
test.py
theme.py
./README.rst
./__init__.py
./comments.py
./email_obfuscator.py
./page.py
./rst.py
./rst_ext.py
./test.py
./theme.py
./themes
./themes/
./themes/balazar
./themes/champi
./themes/ec_base
./themes/green_roses
./themes/ltvda
./themes/oomadness
./themes/oomadness2
./themes/balazar/static
./themes/balazar/theme.conf
./themes/balazar/static/balazar.css
./themes/balazar/static/balazar_bar1.jpeg
./themes/balazar/static/balazar_bar1.xcf
./themes/balazar/static/balazar_bar2.jpeg
./themes/balazar/static/balazar_bar2.xcf
./themes/balazar/static/balazar_titre.png
./themes/champi/static
./themes/champi/theme.conf
./themes/champi/static/champi.css
./themes/champi/static/champi.svg
./themes/champi/static/champi_fond.png
./themes/champi/static/champi_fond.svg
./themes/ec_base/static
./themes/ec_base/theme.conf
./themes/ec_base/static/ec_base.css
./themes/ec_base/static/imageviewer.js
./themes/ec_base/static/sql.js
./themes/green_roses/static
./themes/green_roses/theme.conf
./themes/green_roses/static/green_roses.css
./themes/ltvda/static
./themes/ltvda/theme.conf
./themes/ltvda/static/fleur.svg
./themes/ltvda/static/ltvda.css
./themes/ltvda/static/lyre4.svg
./themes/oomadness/static
./themes/oomadness/theme.conf
./themes/oomadness/static/mini_oomadness.png
./themes/oomadness/static/oomadness.css
./themes/oomadness/static/oomadness.png
./themes/oomadness/static/oomadness_barre_blanc.png
./themes/oomadness2/static
./themes/oomadness2/theme.conf
./themes/oomadness2/static/mini_oomadness.png
./themes/oomadness2/static/oomadness.png
./themes/oomadness2/static/oomadness2.css
./themes/oomadness2/static/oomadness_barre_blanc.png
eClaircie.egg-info/PKG-INFO
eClaircie.egg-info/SOURCES.txt
eClaircie.egg-info/dependency_links.txt
eClaircie.egg-info/not-zip-safe
eClaircie.egg-info/top_level.txt
example_site/2014_05_28_message_en_francais.rst
example_site/2014_05_28_message_en_francais_comments.inc
example_site/2014_05_29_post_in_english.rst
example_site/2014_05_30_bilingual_post.rst
example_site/archives.rst
