Metadata-Version: 1.1
Name: eClaircie
Version: 0.3
Summary: éClaircie is a 100% static and cloud-less blog engine.
Home-page: https://bitbucket.org/jibalamy/eclaircie
Author: Lamy Jean-Baptiste (Jiba)
Author-email: <jibalamy@free.fr>
License: GPLv3+
Platform: UNKNOWN
Classifier: Development Status :: 4 - Beta
Classifier: Programming Language :: Python :: 3
Classifier: License :: OSI Approved :: GNU General Public License v3 or later (GPLv3+)
Classifier: Operating System :: POSIX :: Linux
Classifier: Environment :: Web Environment
Classifier: Topic :: Internet :: WWW/HTTP :: Site Management
Requires: pillow
